ncbi_db/MMlib3.py
ncbi_db/__init__.py
ncbi_db/_version.py
ncbi_db/ncbi_assembly.py
ncbi_db/ncbi_db_info.py
ncbi_db/ncbi_lib.py
ncbi_db/ncbi_pubmed.py
ncbi_db/ncbi_search.py
ncbi_db/ncbi_sequences.py
ncbi_db/ncbi_taxonomy.py
ncbi_db/ncbi_taxonomy_tree.py
ncbi_db/ncbi_taxonomy_tree_db.py
ncbi_db/parse_genbank.py
ncbi_db/search_ncbi_entries.py
ncbi_db-0.1.1.dist-info/METADATA
ncbi_db-0.1.1.dist-info/WHEEL
ncbi_db-0.1.1.dist-info/top_level.txt
ncbi_db-0.1.1.dist-info/RECORD
