Metadata-Version: 2.1
Name: ncbi-db
Version: 0.1.1
Summary: Collection of scripts that wrap the Entrez Bio python module, to query and download portions of NCBI databases
Home-page: https://github.com/pypa/ncbi_db
Author: Marco Mariotti
Author-email: marco.mariotti@ub.edu
Classifier: Programming Language :: Python :: 3
Classifier: License :: OSI Approved :: MIT License
Classifier: Operating System :: OS Independent
Requires-Python: >=3.6
Requires-Dist: biopython
Requires-Dist: ete3
Requires-Dist: lxml
Requires-Dist: six
Requires-Dist: easyterm
